tfkbnufft/__init__.py
tfkbnufft/kbmodule.py
tfkbnufft/kbnufft.py
tfkbnufft/mri/__init__.py
tfkbnufft/mri/dcomp_calc.py
tfkbnufft/nufft/__init__.py
tfkbnufft/nufft/fft_functions.py
tfkbnufft/nufft/interp_functions.py
tfkbnufft/nufft/utils.py
tfkbnufft/tests/__init__.py
tfkbnufft/tests/kbnufft_test.py
tfkbnufft/tests/ndft_test.py
tfkbnufft/tests/utils.py
tfkbnufft/tests/nufft/__init__.py
tfkbnufft/tests/nufft/fft_functions_test.py
tfkbnufft/tests/nufft/interp_functions_test.py
tfkbnufft/utils/__init__.py
tfkbnufft/utils/itertools.py
tfkbnufft-0.2.5.dist-info/LICENSE
tfkbnufft-0.2.5.dist-info/METADATA
tfkbnufft-0.2.5.dist-info/WHEEL
tfkbnufft-0.2.5.dist-info/top_level.txt
tfkbnufft-0.2.5.dist-info/RECORD
