Metadata-Version: 2.1
Name: tfkbnufft
Version: 0.2.5
Summary: A robust, easy-to-deploy non-uniform Fast Fourier Transform in TensorFlow.
Home-page: https://github.com/zaccharieramzi/tfkbnufft
Download-URL: https://github.com/zaccharieramzi/tfkbnufft
Author: Zaccharie Ramzi
Author-email: zaccharie.ramzi@inria.fr
License: MIT
Keywords: MRI,tensorflow
Classifier: Environment :: Console
Classifier: Natural Language :: English
Classifier: Development Status :: 4 - Beta
Classifier: Topic :: Scientific/Engineering :: Artificial Intelligence
Classifier: License :: OSI Approved :: MIT License
Classifier: Programming Language :: Python :: 3
Classifier: Programming Language :: Python :: 3.7
Requires-Python: >=3.5
License-File: LICENSE
Requires-Dist: tensorflow (>=2.1.0)
Requires-Dist: numpy
Requires-Dist: scipy
